flask_aerospike/__init__.py
flask_aerospike/_version.py
flask_aerospike/session.py
flask_aerospike-0.0.1.dist-info/AUTHORS.md
flask_aerospike-0.0.1.dist-info/METADATA
flask_aerospike-0.0.1.dist-info/WHEEL
flask_aerospike-0.0.1.dist-info/top_level.txt
flask_aerospike-0.0.1.dist-info/RECORD
